FIFO/FIFO_cache.v
module async_to_sync_fifo_ctrl #(
    parameter DATA_WIDTH = 8,
    parameter FIFO_DEPTH = 16,
    parameter ADDR_WIDTH = 4)(
        input wire async_wr_req,
        input wire[DATA_WIDTH-1:0] async_din,

        input wire clk_cache,
        input wire rst_n,
        input wire rd_en,

        output wire [DATA_WIDTH-1:0] dout,
        output wire empty,
        output wire full
    );

    reg [2:0] wr_req_sync;

    always @(posedge clk_cache or negedge rst_n) begin
        if(!rst_n) begin 
            wr_req_sync <= 3'b000;
        end else begin
            wr_req_sync <= {wr_req_sync[1:0], async_wr_req};
        end
    end

    reg [DATA_WIDTH-1:0] din_reg;
    wire wr_en;

    always @(posedge clk_cache or negedge rst_n) begin
        if (!rst_n) begin
            din_reg <= {DATA_WIDTH{1'b0}};
        end else if (async_wr_req) begin
            din_reg <= async_din;
        end
    end

    assign wr_en = (wr_req_sync[1] && !wr_req_sync[2]) && !full;

    reg [DATA_WIDTH-1:0] fifo_ram [FIFO_DEPTH-1:0];
    reg [ADDR_WIDTH:0] wr_ptr;
    reg [ADDR_WIDTH:0] rd_ptr;

    always @(posedge clk_cache or negedge rst_n) begin
        if(!rst_n) begin
            wr_ptr <= 0;
        end else if(wr_en) begin
            fifo_ram[wr_ptr[ADDR_WIDTH-1:0]] <= din_reg;
            wr_ptr <= wr_ptr + 1'b1;
        end
    end


    always @(posedge clk_cache or negedge rst_n) begin
        if(!rst_n) begin
            rd_ptr <= 0;
        end else if (rd_en && !empty) begin
            rd_ptr <= rd_ptr + 1'b1;
        end
    end
    

    assign dout = fifo_ram[rd_ptr[ADDR_WIDTH-1:0]];
    assign empty = (wr_ptr == rd_ptr);
    assign full = (wr_ptr[ADDR_WIDTH] != rd_ptr[ADDR_WIDTH]) &&
    (wr_ptr[ADDR_WIDTH-1:0] == rd_ptr[ADDR_WIDTH-1:0]);

endmodule

FIFO/tb_FIFO_cache.v
`timescale 1ps/1ps


module tb_async_to_sync_fifo;

    parameter DATA_WIDTH = 8;
    parameter FIFO_DEPTH = 4;
    parameter ADDR_WIDTH = 2;

    reg async_wr_req;
    reg [DATA_WIDTH-1:0] async_din;
    reg clk_cache;
    reg rst_n;
    reg rd_en;

    wire [DATA_WIDTH-1:0] dout;
    wire empty;
    wire full;

    async_to_sync_fifo_ctrl #(
        .DATA_WIDTH(DATA_WIDTH),
        .FIFO_DEPTH(FIFO_DEPTH),
        .ADDR_WIDTH(ADDR_WIDTH)
    ) uut (
        .async_wr_req(async_wr_req),
        .async_din(async_din),
        .clk_cache(clk_cache),
        .rst_n(rst_n),
        .rd_en(rd_en),
        .dout(dout),
        .empty(empty),
        .full(full)
    );

    always #5000 clk_cache = ~clk_cache;

    initial begin
        $dumpfile("tb_FIFO_cache.vcd");
        $dumpvars(0, uut);

        clk_cache = 0;
        rst_n = 0;
        async_wr_req = 0;
        async_din = 0;
        rd_en = 0;

        #25000;
        rst_n = 1;
        #5000;

        $display("FIFO Empty: %b, Full: %b", empty, full);

        //#9995;
        async_din = 8'hAA;
        async_wr_req = 1;
        #20005;

        async_wr_req = 0;
        #50005;

        $display("[%0t ps] >> 5ps", $time);
/*
        #20000;
        $display("[%0t ps] >> 20000ps", $time);

        begin: write_loop
            integer i;
            for(i = 1; i <= 16; i = i + 1) begin
                #23500;
                async_din = i;
                async_wr_req = 1;
                #16500;
                async_wr_req = 0;
            end
        end

        #20000;
        $display("[%0t ps] >> 16 bit finished writing", $time);
        $display(" wr_ptr = 5'b%b", uut.wr_ptr);
        $display("rd_ptr = 5'b%b", uut.rd_ptr);
        $display("Empty: %b, Full: %b", empty, full);

        #10000;
        async_din = 8'hBB;
        async_wr_req = 1;
        #20000;
        async_wr_req = 0;
        if(uut.fifo_ram[0] == 8'h01) begin
            $display("[%0t ps] >> 1st data read successfully", $time);
        end

        #10000;
        @(posedge clk_cache);
        rd_en = 1;
        $display("[%0t ps] >> rd_en = 1", $time);
        repeat(18) begin
            @(posedge clk_cache);
            #100;
            $display("dout = 8'h%h ,Empty = %b",dout, empty);
        end

        #50000;
        $display("[%0t ps] CDC reset", $time);
*/
        $finish;

    end
endmodule

FIFO/dump.vcd
$date
	Tue Jun 16 09:48:24 2026
$end
$version
	Icarus Verilog
$end
$timescale
	1ps
$end
$scope module tb_async_to_sync_fifo $end
$scope module uut $end
$var reg 8 ! \fifo_ram[0] [7:0] $end
$upscope $end
$upscope $end
$scope module tb_async_to_sync_fifo $end
$scope module uut $end
$var reg 8 " \fifo_ram[1] [7:0] $end
$upscope $end
$upscope $end
$scope module tb_async_to_sync_fifo $end
$scope module uut $end
$var reg 8 # \fifo_ram[2] [7:0] $end
$upscope $end
$upscope $end
$scope module tb_async_to_sync_fifo $end
$scope module uut $end
$var reg 8 $ \fifo_ram[3] [7:0] $end
$upscope $end
$upscope $end
$scope module tb_async_to_sync_fifo $end
$var wire 1 % full $end
$var wire 1 & empty $end
$var wire 8 ' dout [7:0] $end
$var reg 8 ( async_din [7:0] $end
$var reg 1 ) async_wr_req $end
$var reg 1 * clk_cache $end
$var reg 1 + rd_en $end
$var reg 1 , rst_n $end
$scope begin dump_ram[0] $end
$upscope $end
$scope begin dump_ram[1] $end
$upscope $end
$scope begin dump_ram[2] $end
$upscope $end
$scope begin dump_ram[3] $end
$upscope $end
$scope module uut $end
$var wire 8 - async_din [7:0] $end
$var wire 1 ) async_wr_req $end
$var wire 1 * clk_cache $end
$var wire 8 . dout [7:0] $end
$var wire 1 % full $end
$var wire 1 + rd_en $end
$var wire 1 , rst_n $end
$var wire 1 / wr_en $end
$var wire 1 & empty $end
$var reg 8 0 din_reg [7:0] $end
$var reg 3 1 rd_ptr [2:0] $end
$var reg 3 2 wr_ptr [2:0] $end
$var reg 3 3 wr_req_sync [2:0] $end
$upscope $end
$upscope $end
$enddefinitions $end
#0
$dumpvars
b0 3
b0 2
b0 1
b0 0
0/
bx .
b0 -
0,
0+
0*
0)
b0 (
bx '
1&
0%
bx $
bx #
bx "
bx !
$end
#5000
1*
#10000
0*
#15000
1*
#20000
0*
#25000
1*
1,
#30000
0*
1)
b10101010 (
b10101010 -
#35000
b1 3
b10101010 0
1*
#40000
0*
#45000
1/
b11 3
1*
#50000
0*
0)
#55000
0/
b110 3
0&
b1 2
b10101010 !
b10101010 '
b10101010 .
1*
#60000
0*
#65000
b100 3
1*
#70000
0*
#75000
b0 3
1*
